oneNeuron/__init__.py
oneNeuron/perceptron.py
Oneneuron_pypi_divyakolapan97-0.0.2.dist-info/LICENSE
Oneneuron_pypi_divyakolapan97-0.0.2.dist-info/METADATA
Oneneuron_pypi_divyakolapan97-0.0.2.dist-info/WHEEL
Oneneuron_pypi_divyakolapan97-0.0.2.dist-info/top_level.txt
Oneneuron_pypi_divyakolapan97-0.0.2.dist-info/RECORD
